Metadata-Version: 2.1
Name: swag-api
Version: 0.0.1
Summary: API service for SWAG data
Home-page: https://github.com/Netflix-Skunkworks/swag-api
Author: The SWAG developers
License: Apache 2.0
Platform: UNKNOWN
